ecmwfapi/__init__.py
ecmwfapi/api.py
ecmwf_api_client-1.6.4.dist-info/LICENSE
ecmwf_api_client-1.6.4.dist-info/METADATA
ecmwf_api_client-1.6.4.dist-info/WHEEL
ecmwf_api_client-1.6.4.dist-info/top_level.txt
ecmwf_api_client-1.6.4.dist-info/zip-safe
ecmwf_api_client-1.6.4.dist-info/RECORD
